[
	{
		"EventID": "99C_MSQ_01_Periville_success",
		"Level": 35,
		"CreatureType": "MSQ+",
		"UniversalExpAmount": 11000,
		"CurrencyReward": 9750,
		"ItemReward": "QuestReward_WF_Spear",
		"ItemRewardQty": 0,
		"CategoricalProgressionReward": 0,
		"TerritoryStanding": 250,
		"AzothReward": 20,
		"AzothRewardChance": 1,
		"EmitTelemetry": true
	},
	{
		"EventID": "99C_MSQ_02_Karburg_success",
		"Level": 36,
		"CreatureType": "MSQ",
		"UniversalExpAmount": 12000,
		"CurrencyReward": 6600,
		"ItemReward": "CRX_QuestReward_WF_MSQ_VoidGauntlet",
		"ItemRewardQty": 0,
		"CategoricalProgressionReward": 0,
		"TerritoryStanding": 250,
		"AzothReward": 10,
		"AzothRewardChance": 1,
		"EmitTelemetry": true
	},
	{
		"EventID": "99C_MSQ_03_AncientBridge_success",
		"Level": 36,
		"CreatureType": "MSQ+",
		"UniversalExpAmount": 12000,
		"CurrencyReward": 9900,
		"ItemReward": "QuestReward_WF_Longsword",
		"ItemRewardQty": 0,
		"CategoricalProgressionReward": 0,
		"TerritoryStanding": 175,
		"AzothReward": 20,
		"AzothRewardChance": 1,
		"EmitTelemetry": true
	},
	{
		"EventID": "99C_MSQ_04_Settlement01_success",
		"Level": 36,
		"CreatureType": "MSQ-",
		"UniversalExpAmount": 13000,
		"CurrencyReward": 1650,
		"ItemReward": "House_HousingItem_Settler_Decor_Desk_ClothArrangement01",
		"ItemRewardQty": 0,
		"CategoricalProgressionReward": 0,
		"TerritoryStanding": 250,
		"AzothReward": 5,
		"AzothRewardChance": 1,
		"EmitTelemetry": true
	},
	{
		"EventID": "99C_MSQ_05_FindMorgaine_success",
		"Level": 36,
		"CreatureType": "MSQ+",
		"UniversalExpAmount": 13000,
		"CurrencyReward": 9900,
		"ItemReward": "QuestReward_WF_Greataxe",
		"ItemRewardQty": 0,
		"CategoricalProgressionReward": 0,
		"TerritoryStanding": 100,
		"AzothReward": 20,
		"AzothRewardChance": 1,
		"EmitTelemetry": true
	},
	{
		"EventID": "99C_MSQ_06_WitchMagic_success",
		"Level": 37,
		"CreatureType": "MSQ",
		"UniversalExpAmount": 14000,
		"CurrencyReward": 6700,
		"ItemReward": "QuestReward_WF_Ring",
		"ItemRewardQty": 0,
		"CategoricalProgressionReward": 0,
		"TerritoryStanding": 250,
		"AzothReward": 10,
		"AzothRewardChance": 1,
		"EmitTelemetry": true
	},
	{
		"EventID": "99C_MSQ_07_DestroyBarrier_success",
		"Level": 37,
		"CreatureType": "MSQ-",
		"UniversalExpAmount": 14000,
		"CurrencyReward": 1675,
		"ItemReward": "House_HousingItem_Writing_OpenBook",
		"ItemRewardQty": 0,
		"CategoricalProgressionReward": 0,
		"TerritoryStanding": 175,
		"AzothReward": 5,
		"AzothRewardChance": 1,
		"EmitTelemetry": true
	},
	{
		"EventID": "99C_MSQ_08_Settlement02_success",
		"Level": 37,
		"CreatureType": "MSQ-",
		"UniversalExpAmount": 15000,
		"CurrencyReward": 1675,
		"ItemReward": "foodcont4",
		"ItemRewardQty": 5,
		"CategoricalProgressionReward": 0,
		"TerritoryStanding": 100,
		"AzothReward": 5,
		"AzothRewardChance": 1,
		"EmitTelemetry": true
	},
	{
		"EventID": "99C_MSQ_09_Canopus_success",
		"Level": 38,
		"CreatureType": "MSQ",
		"UniversalExpAmount": 15000,
		"CurrencyReward": 6800,
		"ItemReward": "CRX_QuestReward_WF_MSQ_Rapier",
		"ItemRewardQty": 0,
		"CategoricalProgressionReward": 0,
		"TerritoryStanding": 100,
		"AzothReward": 10,
		"AzothRewardChance": 1,
		"EmitTelemetry": true
	},
	{
		"EventID": "99C_MSQ_10_Andrometus_success",
		"Level": 39,
		"CreatureType": "MSQ+",
		"UniversalExpAmount": 15000,
		"CurrencyReward": 10350,
		"ItemReward": "QuestReward_WF_BOW",
		"ItemRewardQty": 0,
		"CategoricalProgressionReward": 0,
		"TerritoryStanding": 175,
		"AzothReward": 20,
		"AzothRewardChance": 1,
		"EmitTelemetry": true
	},
	{
		"EventID": "99C_MSQ_11_Lepus_success",
		"Level": 39,
		"CreatureType": "MSQ",
		"UniversalExpAmount": 15000,
		"CurrencyReward": 6900,
		"ItemReward": "TinctureBlightT5",
		"ItemRewardQty": 5,
		"CategoricalProgressionReward": 0,
		"TerritoryStanding": 250,
		"AzothReward": 10,
		"AzothRewardChance": 1,
		"EmitTelemetry": true
	},
	{
		"EventID": "99C_MSQ_12_Vector_success",
		"Level": 40,
		"CreatureType": "MSQ-",
		"UniversalExpAmount": 15000,
		"CurrencyReward": 1750,
		"ItemReward": "Darkness_AzothStaff_T3",
		"ItemRewardQty": 0,
		"CategoricalProgressionId": "AzothStaff",
		"CategoricalProgressionReward": 1,
		"TerritoryStanding": 175,
		"AzothReward": 5,
		"AzothRewardChance": 1,
		"EmitTelemetry": true
	},
	{
		"EventID": "IO_99C_MSQ2_WitchyGlyph_interact",
		"Level": 0,
		"CreatureType": "Quest",
		"UniversalExpAmount": 0,
		"CurrencyReward": 0,
		"ItemRewardQty": 0,
		"CategoricalProgressionReward": 0,
		"TerritoryStanding": 0,
		"AzothReward": 0,
		"AzothRewardChance": 0,
		"EmitTelemetry": true
	},
	{
		"EventID": "IO_99C_MSQ2_RitualObject_interact",
		"Level": 0,
		"CreatureType": "Quest",
		"UniversalExpAmount": 0,
		"CurrencyReward": 0,
		"ItemRewardQty": 0,
		"CategoricalProgressionReward": 0,
		"TerritoryStanding": 0,
		"AzothReward": 0,
		"AzothRewardChance": 0,
		"EmitTelemetry": true
	},
	{
		"EventID": "IO_99C_MSQ2_RitualObject2_interact",
		"Level": 0,
		"CreatureType": "Quest",
		"UniversalExpAmount": 0,
		"CurrencyReward": 0,
		"ItemRewardQty": 0,
		"CategoricalProgressionReward": 0,
		"TerritoryStanding": 0,
		"AzothReward": 0,
		"AzothRewardChance": 0,
		"EmitTelemetry": true
	},
	{
		"EventID": "IO_99C_MSQ2_RitualObject3_interact",
		"Level": 0,
		"CreatureType": "Quest",
		"UniversalExpAmount": 0,
		"CurrencyReward": 0,
		"ItemRewardQty": 0,
		"CategoricalProgressionReward": 0,
		"TerritoryStanding": 0,
		"AzothReward": 0,
		"AzothRewardChance": 0,
		"EmitTelemetry": true
	},
	{
		"EventID": "IO_99C_MSQ2_GlowingMushroom_interact",
		"Level": 0,
		"CreatureType": "Quest",
		"UniversalExpAmount": 0,
		"CurrencyReward": 0,
		"ItemRewardQty": 0,
		"CategoricalProgressionReward": 0,
		"TerritoryStanding": 0,
		"AzothReward": 0,
		"AzothRewardChance": 0,
		"EmitTelemetry": true
	},
	{
		"EventID": "IO_99C_MSQ2_ShakingCoffinA_interact",
		"Level": 0,
		"CreatureType": "Quest",
		"UniversalExpAmount": 0,
		"CurrencyReward": 0,
		"ItemRewardQty": 0,
		"CategoricalProgressionReward": 0,
		"TerritoryStanding": 0,
		"AzothReward": 0,
		"AzothRewardChance": 0,
		"EmitTelemetry": true
	},
	{
		"EventID": "IO_99C_MSQ2_ShakingCoffinB_interact",
		"Level": 0,
		"CreatureType": "Quest",
		"UniversalExpAmount": 0,
		"CurrencyReward": 0,
		"ItemRewardQty": 0,
		"CategoricalProgressionReward": 0,
		"TerritoryStanding": 0,
		"AzothReward": 0,
		"AzothRewardChance": 0,
		"EmitTelemetry": true
	},
	{
		"EventID": "IO_99C_MSQ2_ShakingCoffinC_interact",
		"Level": 0,
		"CreatureType": "Quest",
		"UniversalExpAmount": 0,
		"CurrencyReward": 0,
		"ItemRewardQty": 0,
		"CategoricalProgressionReward": 0,
		"TerritoryStanding": 0,
		"AzothReward": 0,
		"AzothRewardChance": 0,
		"EmitTelemetry": true
	},
	{
		"EventID": "IO_99C_MSQ2_CorpseTorchA_interact",
		"Level": 0,
		"CreatureType": "Quest",
		"UniversalExpAmount": 0,
		"CurrencyReward": 0,
		"ItemRewardQty": 0,
		"CategoricalProgressionReward": 0,
		"TerritoryStanding": 0,
		"AzothReward": 0,
		"AzothRewardChance": 0,
		"EmitTelemetry": true
	},
	{
		"EventID": "IO_99C_MSQ2_CorpseTorchB_interact",
		"Level": 0,
		"CreatureType": "Quest",
		"UniversalExpAmount": 0,
		"CurrencyReward": 0,
		"ItemRewardQty": 0,
		"CategoricalProgressionReward": 0,
		"TerritoryStanding": 0,
		"AzothReward": 0,
		"AzothRewardChance": 0,
		"EmitTelemetry": true
	},
	{
		"EventID": "IO_99C_MSQ2_CorpseTorchC_interact",
		"Level": 0,
		"CreatureType": "Quest",
		"UniversalExpAmount": 0,
		"CurrencyReward": 0,
		"ItemRewardQty": 0,
		"CategoricalProgressionReward": 0,
		"TerritoryStanding": 0,
		"AzothReward": 0,
		"AzothRewardChance": 0,
		"EmitTelemetry": true
	},
	{
		"EventID": "IO_99C_MSQ2_CorpseTorchD_interact",
		"Level": 0,
		"CreatureType": "Quest",
		"UniversalExpAmount": 0,
		"CurrencyReward": 0,
		"ItemRewardQty": 0,
		"CategoricalProgressionReward": 0,
		"TerritoryStanding": 0,
		"AzothReward": 0,
		"AzothRewardChance": 0,
		"EmitTelemetry": true
	},
	{
		"EventID": "IO_99C_MSQ2_CorpseTorchE_interact",
		"Level": 0,
		"CreatureType": "Quest",
		"UniversalExpAmount": 0,
		"CurrencyReward": 0,
		"ItemRewardQty": 0,
		"CategoricalProgressionReward": 0,
		"TerritoryStanding": 0,
		"AzothReward": 0,
		"AzothRewardChance": 0,
		"EmitTelemetry": true
	},
	{
		"EventID": "IO_99C_MSQ2_GlowingOrbsA_interact",
		"Level": 0,
		"CreatureType": "Quest",
		"UniversalExpAmount": 0,
		"CurrencyReward": 0,
		"ItemRewardQty": 0,
		"CategoricalProgressionReward": 0,
		"TerritoryStanding": 0,
		"AzothReward": 0,
		"AzothRewardChance": 0,
		"EmitTelemetry": true
	},
	{
		"EventID": "IO_99C_MSQ2_GlowingOrbsB_interact",
		"Level": 0,
		"CreatureType": "Quest",
		"UniversalExpAmount": 0,
		"CurrencyReward": 0,
		"ItemRewardQty": 0,
		"CategoricalProgressionReward": 0,
		"TerritoryStanding": 0,
		"AzothReward": 0,
		"AzothRewardChance": 0,
		"EmitTelemetry": true
	},
	{
		"EventID": "IO_99C_MSQ2_GlowingOrbsC_interact",
		"Level": 0,
		"CreatureType": "Quest",
		"UniversalExpAmount": 0,
		"CurrencyReward": 0,
		"ItemRewardQty": 0,
		"CategoricalProgressionReward": 0,
		"TerritoryStanding": 0,
		"AzothReward": 0,
		"AzothRewardChance": 0,
		"EmitTelemetry": true
	},
	{
		"EventID": "IO_99C_MSQ2_GlowingOrbsD_interact",
		"Level": 0,
		"CreatureType": "Quest",
		"UniversalExpAmount": 0,
		"CurrencyReward": 0,
		"ItemRewardQty": 0,
		"CategoricalProgressionReward": 0,
		"TerritoryStanding": 0,
		"AzothReward": 0,
		"AzothRewardChance": 0,
		"EmitTelemetry": true
	},
	{
		"EventID": "IO_99C_MSQ2_AncientDevice_interact",
		"Level": 0,
		"CreatureType": "Quest",
		"UniversalExpAmount": 0,
		"CurrencyReward": 0,
		"ItemRewardQty": 0,
		"CategoricalProgressionReward": 0,
		"TerritoryStanding": 0,
		"AzothReward": 0,
		"AzothRewardChance": 0,
		"EmitTelemetry": true
	},
	{
		"EventID": "IO_99C_MSQ2_AncientConsole_interact",
		"Level": 0,
		"CreatureType": "Quest",
		"UniversalExpAmount": 0,
		"CurrencyReward": 0,
		"ItemRewardQty": 0,
		"CategoricalProgressionReward": 0,
		"TerritoryStanding": 0,
		"AzothReward": 0,
		"AzothRewardChance": 0,
		"EmitTelemetry": true
	},
	{
		"EventID": "IO_99C_MSQ2_AncientChest_interact",
		"Level": 0,
		"CreatureType": "Quest",
		"UniversalExpAmount": 0,
		"CurrencyReward": 0,
		"ItemRewardQty": 0,
		"CategoricalProgressionReward": 0,
		"TerritoryStanding": 0,
		"AzothReward": 0,
		"AzothRewardChance": 0,
		"EmitTelemetry": true
	},
	{
		"EventID": "IO_99C_MSQ2_AncientChestBlight_interact",
		"Level": 0,
		"CreatureType": "Quest",
		"UniversalExpAmount": 0,
		"CurrencyReward": 0,
		"ItemRewardQty": 0,
		"CategoricalProgressionReward": 0,
		"TerritoryStanding": 0,
		"AzothReward": 0,
		"AzothRewardChance": 0,
		"EmitTelemetry": true
	},
	{
		"EventID": "IO_99C_MSQ2_AncientShieldDevice_interact",
		"Level": 0,
		"CreatureType": "Quest",
		"UniversalExpAmount": 0,
		"CurrencyReward": 0,
		"ItemRewardQty": 0,
		"CategoricalProgressionReward": 0,
		"TerritoryStanding": 0,
		"AzothReward": 0,
		"AzothRewardChance": 0,
		"EmitTelemetry": true
	},
	{
		"EventID": "IO_99C_MSQ2_AncientShieldDevice2_interact",
		"Level": 0,
		"CreatureType": "Quest",
		"UniversalExpAmount": 0,
		"CurrencyReward": 0,
		"ItemRewardQty": 0,
		"CategoricalProgressionReward": 0,
		"TerritoryStanding": 0,
		"AzothReward": 0,
		"AzothRewardChance": 0,
		"EmitTelemetry": true
	},
	{
		"EventID": "IO_99C_MSQ2_AncientShieldDevice3_interact",
		"Level": 0,
		"CreatureType": "Quest",
		"UniversalExpAmount": 0,
		"CurrencyReward": 0,
		"ItemRewardQty": 0,
		"CategoricalProgressionReward": 0,
		"TerritoryStanding": 0,
		"AzothReward": 0,
		"AzothRewardChance": 0,
		"EmitTelemetry": true
	},
	{
		"EventID": "IO_99C_MorgainesTruth_CinematicStart_interact",
		"Level": 0,
		"CreatureType": "Quest",
		"UniversalExpAmount": 0,
		"CurrencyReward": 0,
		"ItemRewardQty": 0,
		"CategoricalProgressionReward": 0,
		"TerritoryStanding": 0,
		"AzothReward": 0,
		"AzothRewardChance": 0,
		"EmitTelemetry": true
	},
	{
		"EventID": "IO_99C_MSQ2_MorgainesCaveDoor_interact",
		"Level": 0,
		"CreatureType": "Quest",
		"UniversalExpAmount": 0,
		"CurrencyReward": 0,
		"ItemRewardQty": 0,
		"CategoricalProgressionReward": 0,
		"TerritoryStanding": 0,
		"AzothReward": 0,
		"AzothRewardChance": 0,
		"EmitTelemetry": true
	},
	{
		"EventID": "IO_99C_MSQ2_MorgainesCaveDoor_Permanent_interact",
		"Level": 0,
		"CreatureType": "Quest",
		"UniversalExpAmount": 0,
		"CurrencyReward": 0,
		"ItemRewardQty": 0,
		"CategoricalProgressionReward": 0,
		"TerritoryStanding": 0,
		"AzothReward": 0,
		"AzothRewardChance": 0,
		"EmitTelemetry": true
	},
	{
		"EventID": "99C_Isabella_whisper_WF_01_interact",
		"Level": 0,
		"CreatureType": "Quest",
		"UniversalExpAmount": 0,
		"CurrencyReward": 0,
		"ItemRewardQty": 0,
		"CategoricalProgressionReward": 0,
		"TerritoryStanding": 0,
		"AzothReward": 0,
		"AzothRewardChance": 0,
		"WhisperID": "99C_Isabella_whisper_WF_01",
		"EmitTelemetry": true
	},
	{
		"EventID": "99C_Isabella_whisper_WF_02_interact",
		"Level": 0,
		"CreatureType": "Quest",
		"UniversalExpAmount": 0,
		"CurrencyReward": 0,
		"ItemRewardQty": 0,
		"CategoricalProgressionReward": 0,
		"TerritoryStanding": 0,
		"AzothReward": 0,
		"AzothRewardChance": 0,
		"WhisperID": "99C_Isabella_whisper_WF_02",
		"EmitTelemetry": true
	},
	{
		"EventID": "99C_Isabella_whisper_WF_03_interact",
		"Level": 0,
		"CreatureType": "Quest",
		"UniversalExpAmount": 0,
		"CurrencyReward": 0,
		"ItemRewardQty": 0,
		"CategoricalProgressionReward": 0,
		"TerritoryStanding": 0,
		"AzothReward": 0,
		"AzothRewardChance": 0,
		"WhisperID": "99C_Isabella_whisper_WF_03",
		"EmitTelemetry": true
	},
	{
		"EventID": "99C_Morgaine_VoicedLoreNote_01_interact",
		"Level": 0,
		"CreatureType": "Quest",
		"UniversalExpAmount": 0,
		"CurrencyReward": 0,
		"ItemRewardQty": 0,
		"CategoricalProgressionReward": 0,
		"TerritoryStanding": 0,
		"AzothReward": 0,
		"AzothRewardChance": 0,
		"WhisperID": "99C_Morgaine_VoicedLoreNote_01",
		"EmitTelemetry": true
	},
	{
		"EventID": "99C_Morgaine_VoicedLoreNote_02_interact",
		"Level": 0,
		"CreatureType": "Quest",
		"UniversalExpAmount": 0,
		"CurrencyReward": 0,
		"ItemRewardQty": 0,
		"CategoricalProgressionReward": 0,
		"TerritoryStanding": 0,
		"AzothReward": 0,
		"AzothRewardChance": 0,
		"WhisperID": "99C_Morgaine_VoicedLoreNote_02",
		"EmitTelemetry": true
	},
	{
		"EventID": "99C_Morgaine_VoicedLoreNote_03_interact",
		"Level": 0,
		"CreatureType": "Quest",
		"UniversalExpAmount": 0,
		"CurrencyReward": 0,
		"ItemRewardQty": 0,
		"CategoricalProgressionReward": 0,
		"TerritoryStanding": 0,
		"AzothReward": 0,
		"AzothRewardChance": 0,
		"WhisperID": "99C_Morgaine_VoicedLoreNote_03",
		"EmitTelemetry": true
	},
	{
		"EventID": "99C_Morgaine_VoicedLoreNote_04_interact",
		"Level": 0,
		"CreatureType": "Quest",
		"UniversalExpAmount": 0,
		"CurrencyReward": 0,
		"ItemRewardQty": 0,
		"CategoricalProgressionReward": 0,
		"TerritoryStanding": 0,
		"AzothReward": 0,
		"AzothRewardChance": 0,
		"WhisperID": "99C_Morgaine_VoicedLoreNote_04",
		"EmitTelemetry": true
	},
	{
		"EventID": "99C_Morgaine_VoicedLoreNote_05_interact",
		"Level": 0,
		"CreatureType": "Quest",
		"UniversalExpAmount": 0,
		"CurrencyReward": 0,
		"ItemRewardQty": 0,
		"CategoricalProgressionReward": 0,
		"TerritoryStanding": 0,
		"AzothReward": 0,
		"AzothRewardChance": 0,
		"WhisperID": "99C_Morgaine_VoicedLoreNote_05",
		"EmitTelemetry": true
	},
	{
		"EventID": "99C_Morgaine_VoicedLoreNote_06_interact",
		"Level": 0,
		"CreatureType": "Quest",
		"UniversalExpAmount": 0,
		"CurrencyReward": 0,
		"ItemRewardQty": 0,
		"CategoricalProgressionReward": 0,
		"TerritoryStanding": 0,
		"AzothReward": 0,
		"AzothRewardChance": 0,
		"WhisperID": "99C_Morgaine_VoicedLoreNote_06",
		"EmitTelemetry": true
	},
	{
		"EventID": "99C_MSQ_puzzle1_stone1_interact",
		"Level": 0,
		"CreatureType": "Quest",
		"UniversalExpAmount": 0,
		"CurrencyReward": 0,
		"ItemRewardQty": 0,
		"CategoricalProgressionReward": 0,
		"TerritoryStanding": 0,
		"AzothReward": 0,
		"AzothRewardChance": 0,
		"EmitTelemetry": true
	},
	{
		"EventID": "99C_MSQ_puzzle1_stone2_interact",
		"Level": 0,
		"CreatureType": "Quest",
		"UniversalExpAmount": 0,
		"CurrencyReward": 0,
		"ItemRewardQty": 0,
		"CategoricalProgressionReward": 0,
		"TerritoryStanding": 0,
		"AzothReward": 0,
		"AzothRewardChance": 0,
		"EmitTelemetry": true
	},
	{
		"EventID": "IO_99C_MSQ2_BlightBombA_interact",
		"Level": 0,
		"CreatureType": "Quest",
		"UniversalExpAmount": 0,
		"CurrencyReward": 0,
		"ItemRewardQty": 0,
		"CategoricalProgressionReward": 0,
		"TerritoryStanding": 0,
		"AzothReward": 0,
		"AzothRewardChance": 0,
		"EmitTelemetry": true
	},
	{
		"EventID": "IO_99C_MSQ2_BlightBombB_interact",
		"Level": 0,
		"CreatureType": "Quest",
		"UniversalExpAmount": 0,
		"CurrencyReward": 0,
		"ItemRewardQty": 0,
		"CategoricalProgressionReward": 0,
		"TerritoryStanding": 0,
		"AzothReward": 0,
		"AzothRewardChance": 0,
		"EmitTelemetry": true
	},
	{
		"EventID": "IO_99C_MSQ2_BlightBombC_interact",
		"Level": 0,
		"CreatureType": "Quest",
		"UniversalExpAmount": 0,
		"CurrencyReward": 0,
		"ItemRewardQty": 0,
		"CategoricalProgressionReward": 0,
		"TerritoryStanding": 0,
		"AzothReward": 0,
		"AzothRewardChance": 0,
		"EmitTelemetry": true
	},
	{
		"EventID": "IO_99C_MSQ2_AncientChest_1_interact",
		"Level": 0,
		"CreatureType": "Quest",
		"UniversalExpAmount": 0,
		"CurrencyReward": 0,
		"ItemRewardQty": 0,
		"CategoricalProgressionReward": 0,
		"TerritoryStanding": 0,
		"AzothReward": 0,
		"AzothRewardChance": 0,
		"EmitTelemetry": true
	},
	{
		"EventID": "IO_99C_MSQ2_AncientChest_2_interact",
		"Level": 0,
		"CreatureType": "Quest",
		"UniversalExpAmount": 0,
		"CurrencyReward": 0,
		"ItemRewardQty": 0,
		"CategoricalProgressionReward": 0,
		"TerritoryStanding": 0,
		"AzothReward": 0,
		"AzothRewardChance": 0,
		"EmitTelemetry": true
	},
	{
		"EventID": "IO_99C_MSQ2_AncientChest_3_interact",
		"Level": 0,
		"CreatureType": "Quest",
		"UniversalExpAmount": 0,
		"CurrencyReward": 0,
		"ItemRewardQty": 0,
		"CategoricalProgressionReward": 0,
		"TerritoryStanding": 0,
		"AzothReward": 0,
		"AzothRewardChance": 0,
		"EmitTelemetry": true
	}
]